{
  "brews": {
    "ansible": "",
    "aspell": "",
    "autoconf": "",
    "automake": "",
    "bash-completion": "",
    "cairo": "",
    "colordiff": "",
    "coreutils": "",
    "ctags": "",
    "curl": "",
    "dtrx": "",
    "fasd": "",
    "ffmpeg": "",
    "findutils": "with-default-names",
    "flac": "",
    "fpp": "",
    "fzf": "",
    "fswatch": "",
    "gcc": "",
    "gdb": "with-homebrewed-python,with-all-targets",
    "git": "",
    "gnu-sed": "",
    "gnu-tar": "",
    "gnupg": "with-default-names",
    "go": "",
    "graphicsmagick": "",
    "grep": "with-default-names",
    "ispell": "",
    "jpeg": "",
    "jq": "",
    "lame": "",
    "libpng": "",
    "libtiff": "",
    "libtool": "",
    "libyaml": "",
    "llvm": "with-lld,with-clang,with-rtti",
    "netcat": "",
    "nmap": "",
    "nvm": "",
    "openssl": "",
    "pkg-config": "",
    "pcre": "",
    "phantomjs": "",
    "postgresql": "",
    "pyenv": "",
    "readline": "",
    "reattach-to-user-namespace": "wrap-pbcopy-and-pbpaste",
    "rlwrap": "",
    "sloccount": "",
    "sqlite": "",
    "the_silver_searcher": "",
    "tmux": "",
    "tree": "",
    "vim": "without-ruby,without-python",
    "wget": "",
    "youtube-dl": ""
  }
}
